mse_lib_crypto/__init__.py
mse_lib_crypto/conversion.py
mse_lib_crypto/ed25519.py
mse_lib_crypto/error.py
mse_lib_crypto/py.typed
mse_lib_crypto/seal_box.py
mse_lib_crypto/x25519.py
mse_lib_crypto/xsalsa20_poly1305.py
mse_lib_crypto-1.4.dist-info/METADATA
mse_lib_crypto-1.4.dist-info/WHEEL
mse_lib_crypto-1.4.dist-info/top_level.txt
mse_lib_crypto-1.4.dist-info/RECORD
